{
  "header": {
    "category": "economic-update",
    "image": {
      "type": "",
      "url": ""
    },
    "layout": "podcast",
    "link": "http://economicupdate.podbean.com/e/economic-update-big-changes-coming-091014/",
    "podcast": {
      "developer-note": "",
      "length": "58:3",
      "note": "",
      "size": 21060680,
      "type": "audio/mpeg",
      "url": "http://economicupdate.podbean.com/mf/feed/q46cj9/Econ_Update_091014.mp3"
    },
    "show": {
      "category": [
        "News & Politics"
      ],
      "image": {
        "height": 144,
        "url": "http://imglogo.podbean.com/image-logo/594561/Richard-Wolff-Album-Art.jpg",
        "width": 144
      },
      "owner": {
        "email": "jtaubenfeld@garynull.com",
        "name": ""
      },
      "published": {
        "string": "Sun, 01 Mar 2015 21:00:00 +0000",
        "timestamp": "1425261600"
      },
      "subtitle": "New podcast weblog",
      "title": "Economic Update"
    },
    "tags": [
      "News & Politics",
      "economic-update"
    ],
    "title": "Big Changes Coming"
  },
  "title": "Big Changes Coming",
  "date": "2014-09-10 00:00:00 -0400",
  "categories": [
    "economic-update"
  ],
  "content": "<p>Updates on food insecurity, oil disaster economics, politicos go to Wall Street, billionaires buy homes, education In<span class=\"ellipsis\">...</span>\n&lt;!--more--&gt;\nUK and US sustains elites. <br />\nMajor discussions of (1) employers’ movement for a 4-day workweek, and (2) history of socialism vs capitalism (part 1 with part 2 next week) which was also response to many listeners’ questions.\n<br /></p>\n"
}
