{
  "header": {
    "category": "connect-the-dots",
    "image": {
      "type": "",
      "url": ""
    },
    "layout": "podcast",
    "link": "http://connectthedots.podbean.com/e/connect-the-dots-reclaiming-the-commons-032614/",
    "podcast": {
      "developer-note": "",
      "length": "53:27",
      "note": "",
      "size": 12829780,
      "type": "audio/mpeg",
      "url": "http://connectthedots.podbean.com/mf/feed/cjmtui/ConnectTheDots032614.mp3"
    },
    "show": {
      "category": [
        "Health",
        "Alternative Health"
      ],
      "image": {
        "height": 144,
        "url": "http://imglogo.podbean.com/image-logo/324701/Alison_Rose_Levy_AlbumArt.jpg",
        "width": 144
      },
      "owner": {
        "email": "karalee@garynull.com",
        "name": "Progressive Radio Network"
      },
      "published": {
        "string": "Thu, 26 Feb 2015 18:29:44 +0000",
        "timestamp": "1424993384"
      },
      "subtitle": "Connect the Dots promotes health activism, linking personal health to the health of our culture, society, and environment.",
      "title": "Connect The Dots"
    },
    "tags": [
      "Health",
      "Alternative Health",
      "connect-the-dots"
    ],
    "title": "Reclaiming the Commons"
  },
  "title": "Reclaiming the Commons",
  "date": "2014-03-26 00:00:00 -0400",
  "categories": [
    "connect-the-dots"
  ],
  "content": "<p>An interview with David Bollier, author of Think Like a\nCommoner.</p>\n\n<!--more-->\n"
}
