{
  "header": {
    "category": "the-wake-up-call",
    "image": {
      "type": "",
      "url": ""
    },
    "layout": "podcast",
    "link": "http://thewakeupcall.podbean.com/e/gambling-with-%e2%80%98qe%e2%80%99-in-deflationary-times-010515/",
    "podcast": {
      "developer-note": "",
      "length": "57:24",
      "note": "",
      "size": 20669456,
      "type": "audio/mpeg",
      "url": "http://thewakeupcall.podbean.com/mf/feed/yx2wa5/WakeUpCall_010515.mp3"
    },
    "show": {
      "category": [
        "Business",
        "Investing"
      ],
      "image": {
        "height": 144,
        "url": "http://imglogo.podbean.com/image-logo/276914/Richard_Martin_AlbumArt2.jpg",
        "width": 144
      },
      "owner": {
        "email": "karalee@garynull.com",
        "name": "Progressive Radio Network"
      },
      "published": {
        "string": "Mon, 23 Feb 2015 21:03:15 +0000",
        "timestamp": "1424743395"
      },
      "subtitle": "Your Economic Survival?  They're Not Looking Out For You.  We are.",
      "title": "The Wake Up Call"
    },
    "tags": [
      "Business",
      "Investing",
      "the-wake-up-call"
    ],
    "title": "Gambling With ‘QE’ In Deflationary Times"
  },
  "title": "Gambling With ‘QE’ In Deflationary Times",
  "date": "2015-01-05 00:00:00 -0500",
  "categories": [
    "the-wake-up-call"
  ],
  "content": "<p>The 2015 introductory edition… The theme-of-the-year remains “War”.\n<!--more-->\nThe grand unraveling as viewed through the eyes of Japan. <br />\nThe unthinkable amounts of debt jammed into the system by insane central bankers with no possible idea of what they were trying to achieve. <br />\nThis was irrational behavior at its most extreme. <br />\nThe entire edifice must collapse since the debt is totally unpayable. <br />\nJapan is the poster-child of mass irresponsibility by government. <br />\nIt is impossible to analyse the mindset of such incredible, mass stupidity. <br />\nThe entire world is infected. <br />\nThe gravity of all this is unparalleled in all of time. <br />\nCasinos and their future. <br />\nA few words on the TPP which Obama is determined to push through (though no one seems to know why it’s so important to him). <br />\nIt must be stopped.\n<br /></p>\n"
}
