{
  "header": {
    "category": "connect-the-dots",
    "image": {
      "type": "",
      "url": ""
    },
    "layout": "podcast",
    "link": "http://connectthedots.podbean.com/e/connect-the-dots-when-public-health-departments-fail-public-health-080614/",
    "podcast": {
      "developer-note": "",
      "length": "55:19",
      "note": "",
      "size": 19919736,
      "type": "audio/mpeg",
      "url": "http://connectthedots.podbean.com/mf/feed/4s7xaw/ConnectTheDots_080614.mp3"
    },
    "show": {
      "category": [
        "Health",
        "Alternative Health"
      ],
      "image": {
        "height": 144,
        "url": "http://imglogo.podbean.com/image-logo/324701/Alison_Rose_Levy_AlbumArt.jpg",
        "width": 144
      },
      "owner": {
        "email": "karalee@garynull.com",
        "name": "Progressive Radio Network"
      },
      "published": {
        "string": "Wed, 11 Mar 2015 22:29:09 +0000",
        "timestamp": "1426130949"
      },
      "subtitle": "Connect the Dots promotes health activism, linking personal health to the health of our culture, society, and environment.",
      "title": "Connect The Dots"
    },
    "tags": [
      "Health",
      "Alternative Health",
      "connect-the-dots"
    ],
    "title": "When Public Health Departments Fail Public Health"
  },
  "title": "When Public Health Departments Fail Public Health",
  "date": "2014-08-06 00:00:00 -0400",
  "categories": [
    "connect-the-dots"
  ],
  "content": "<p>Interview with Karen Feridun, from Berks Gas Truth, discussing new revelations about the Pennyslvania State Department<span class=\"ellipsis\">...</span>\n&lt;!--more--&gt;\nof Health. <br /></p>\n\n<p><br /></p>\n"
}
