{
  "header": {
    "category": "leid-stories",
    "image": {
      "type": "image",
      "url": "http://leidstories.podbean.com/mf/web/vb9b/Utrice-Leid-Album-Art.jpg"
    },
    "layout": "podcast",
    "link": "http://leidstories.podbean.com/e/leid-stories-the-media-the-marathon-and-mind-control-042313/",
    "podcast": {
      "developer-note": "",
      "length": "52:31",
      "note": "",
      "size": 12607425,
      "type": "audio/mpeg",
      "url": "http://leidstories.podbean.com/mf/feed/3k2zwf/LeidStories042313.mp3"
    },
    "show": {
      "category": [
        "Society & Culture"
      ],
      "image": {
        "height": 144,
        "url": "http://imglogo.podbean.com/image-logo/547423/Utrice-Leid-Album-Art.jpg",
        "width": 144
      },
      "owner": {
        "email": "jtaubenfeld@garynull.com",
        "name": "Progressive Radio Network"
      },
      "published": {
        "string": "Thu, 12 Mar 2015 21:05:57 +0000",
        "timestamp": "1426212357"
      },
      "subtitle": "Stories and news that affect us all",
      "title": "Leid Stories"
    },
    "tags": [
      "Society & Culture",
      "leid-stories"
    ],
    "title": "The Media, the Marathon and Mind Control"
  },
  "title": "The Media, the Marathon and Mind Control",
  "date": "2013-04-23 00:00:00 -0400",
  "categories": [
    "leid-stories"
  ],
  "content": "<p>Continuing with our coursework in media literacy, Leid Stories examines the mainstream media’s self-assigned role in a<span class=\"ellipsis\">...</span>\n&lt;!--more--&gt;\nperceived “national crisis.<br />\n” Coverage of the Boston Marathon bombings and aftermath continues to reflect and reinforce the desired objectives of the state, even at the expense of journalistic independence and integrity. <br />\nThere is a shared mission, after all, and the media are obligated to fulfill its part of the bargain, providing the “information” necessary to maintain order, national identity and the mechanisms of social control.\n<br /></p>\n"
}
