{
  "header": {
    "category": "progressive-radio-news-hour",
    "image": {
      "type": "",
      "url": ""
    },
    "layout": "podcast",
    "link": "http://progressiveradionewshour.podbean.com/e/progressive-radio-news-hour-james-fetzer-120812/",
    "podcast": {
      "developer-note": "",
      "length": "56:09",
      "note": "",
      "size": 13476362,
      "type": "audio/mpeg",
      "url": "http://progressiveradionewshour.podbean.com/mf/feed/u9gncu/Lendman120812.mp3"
    },
    "show": {
      "category": [
        "News & Politics"
      ],
      "image": {
        "height": 144,
        "url": "http://progressiveradionewshour.podbean.com/feed/h",
        "width": 144
      },
      "owner": {
        "email": "h",
        "name": "h"
      },
      "published": {
        "string": "Sun, 22 Feb 2015 23:43:00 +0000",
        "timestamp": "1424666580"
      },
      "subtitle": "h",
      "title": "Progressive Radio News Hour"
    },
    "tags": [
      "News & Politics",
      "progressive-radio-news-hour"
    ],
    "title": "James Fetzer"
  },
  "title": "James Fetzer",
  "date": "2012-12-08 00:00:00 -0700",
  "categories": [
    "progressive-radio-news-hour"
  ],
  "content": "<p>James Fetzer\nFetzer is the distinguished Department of Philosophy McKnight University Professor Emeritus at the<span class=\"ellipsis\">...</span>\n&lt;!--more--&gt;\nUniversity of Minnesota, Duluth.\n<br />\nHe’s a prolific author of numerous articles and over 20 books in the philosophy of science and on the theoretical foundations of computer science, artificial intelligence and cognitive science.\n<br />\nHe’s also the founder of Scholars for 9/11 truth. <br />\nIt’s a non-partisan association of faculty, students, and scholars, dedicated to exposing official lies, removing the shroud of deceit, and revealing truths behind 9/11.\n<br />\nMajor world and national issues will be discussed.\n<br /></p>\n"
}
