{
  "header": {
    "category": "prescriptions-for-health",
    "image": {
      "type": "",
      "url": ""
    },
    "layout": "podcast",
    "link": "http://prescriptionsforhealth.podbean.com/e/prescriptions-for-health-100713/",
    "podcast": {
      "developer-note": "",
      "length": "54:5",
      "note": "",
      "size": 13161012,
      "type": "audio/mpeg",
      "url": "http://prescriptionsforhealth.podbean.com/mf/feed/99hv3t/Prescriptions100713.mp3"
    },
    "show": {
      "category": [
        "Health",
        "Alternative Health"
      ],
      "image": {
        "height": 144,
        "url": "http://imglogo.podbean.com/image-logo/368145/DrLenSeputo_AlbumArt.jpg",
        "width": 144
      },
      "owner": {
        "email": "karalee@garynull.com",
        "name": "Progressive Radio Network"
      },
      "published": {
        "string": "Thu, 05 Mar 2015 22:17:32 +0000",
        "timestamp": "1425611852"
      },
      "subtitle": "Dr. Len and Nurse Vicki discuss various natural and holistic health topics while taking your calls.",
      "title": "Prescriptions For Health"
    },
    "tags": [
      "Health",
      "Alternative Health",
      "prescriptions-for-health"
    ],
    "title": "Prescriptions For Health"
  },
  "title": "Prescriptions For Health",
  "date": "2013-10-07 00:00:00 -0400",
  "categories": [
    "prescriptions-for-health"
  ],
  "content": "<p>How safe is medical care in the US?\nWhat are the challenges doctors face in balancing work and home life?\n&lt;!--more--&gt;\nDoes ownership in medical testing facilities lead to overtesting?\n<br />\nWhat are the leading causes for hospital readmissions?\n<br />\nWhat is the future of urban agriculture?\n<br />\nVicki’s 20-20 tips are:\nThe salsa ingredient that purifies water\nQuotes from a friend\n<br /></p>\n"
}
