{
  "header": {
    "category": "all-together-now",
    "image": {
      "type": "",
      "url": ""
    },
    "layout": "podcast",
    "link": "http://alltogethernow.podbean.com/e/all-together-now-053013/",
    "podcast": {
      "developer-note": "",
      "length": "54:09",
      "note": "",
      "size": 12998008,
      "type": "audio/mpeg",
      "url": "http://alltogethernow.podbean.com/mf/feed/nzf4rr/ATN053013.mp3"
    },
    "show": {
      "category": [
        "News & Politics"
      ],
      "image": {
        "height": 144,
        "url": "http://img.podbean.com/podbean-logo/powered_by_podbean_800x800.jpg",
        "width": 144
      },
      "owner": {
        "email": "karalee@garynull.com",
        "name": "Progressive Radio Network"
      },
      "published": {
        "string": "Fri, 13 Feb 2015 20:17:54 +0000",
        "timestamp": "1423876674"
      },
      "subtitle": "Charlene Spretnak and her guests track the progress of the “Big Make-over,” the cultural and political Relational Shift that is occurring in all fields as a result of recent discoveries that life is far more dynamically interrelated than modern societies have realized.",
      "title": "All Together Now"
    },
    "tags": [
      "News & Politics",
      "all-together-now"
    ],
    "title": "All Together Now"
  },
  "title": "All Together Now",
  "date": "2013-05-30 00:00:00 -0600",
  "categories": [
    "all-together-now"
  ],
  "content": "<p>Eleanor LeCain speaks with Michael Kanter, the co-owner and founder of Cambridge Naturals - a thriving locally owned<span class=\"ellipsis\">...</span>\n&lt;!--more--&gt;\ncommunity business selling natural products - about how strong local businesses are essential for resilient and prosperous communities.\n<br /></p>\n"
}
