{
  "header": {
    "category": "leid-stories",
    "image": {
      "type": "",
      "url": ""
    },
    "layout": "podcast",
    "link": "http://leidstories.podbean.com/e/leid-stories-092914/",
    "podcast": {
      "developer-note": "",
      "length": "53:35",
      "note": "",
      "size": 19292688,
      "type": "audio/mpeg",
      "url": "http://leidstories.podbean.com/mf/feed/cr5uni/LeidStories_092914.mp3"
    },
    "show": {
      "category": [
        "Society & Culture"
      ],
      "image": {
        "height": 144,
        "url": "http://imglogo.podbean.com/image-logo/547423/Utrice-Leid-Album-Art.jpg",
        "width": 144
      },
      "owner": {
        "email": "jtaubenfeld@garynull.com",
        "name": "Progressive Radio Network"
      },
      "published": {
        "string": "Thu, 12 Mar 2015 21:05:57 +0000",
        "timestamp": "1426212357"
      },
      "subtitle": "Stories and news that affect us all",
      "title": "Leid Stories"
    },
    "tags": [
      "Society & Culture",
      "leid-stories"
    ],
    "title": "Leid Stories"
  },
  "title": "Leid Stories",
  "date": "2014-09-30 00:00:00 -0600",
  "categories": [
    "leid-stories"
  ],
  "content": "<p>Wizard of Odd: Obama Ramps Up on Race; Finds There’s No Place Like ‘Home’\nHaving carefully avoided the subject of<span class=\"ellipsis\">...</span>\n&lt;!--more--&gt;\nrace/racism/white supremacy for most of his tenure in office—except to make points about Blacks’ penchant for self-inflicted pathology—President Obama seemed to be ungagging himself. <br />\nBut wait. <br />\nIt was just another tell-them-what-they-want-to-hear moment.\n<br />\nKeynoting the black-tie dinner that caps the Congressional Black Caucus’s annual summit on illusory legislative power, Obama went “home,” touching on issues that remain raw with most of Black America. <br />\nBut just when you think he’s achieving his own “teachable moment,” he gives lets the cat out of the bag. <br />\nIt’s just a hook to introduce Eric Holder as the heir to Thurgood Marshall’s civil-rights legacy (and, possibly, his seat on the US Supreme Court?<br />\n) and a lead-in to “bring souls to the polls” in the November election.\n<br />\nLeid Stories airs last night’s speech and follows with a commentary.<br /></p>\n"
}
