{
  "header": {
    "category": "leid-stories",
    "image": {
      "type": "",
      "url": ""
    },
    "layout": "podcast",
    "link": "http://leidstories.podbean.com/e/leid-stories-obama-goes-a-gunning-in-europe-itching-for-a-fight-060514/",
    "podcast": {
      "developer-note": "",
      "length": "54:27",
      "note": "",
      "size": 13071987,
      "type": "audio/mpeg",
      "url": "http://leidstories.podbean.com/mf/feed/92egqm/LeidStories_060514.mp3"
    },
    "show": {
      "category": [
        "Society & Culture"
      ],
      "image": {
        "height": 144,
        "url": "http://imglogo.podbean.com/image-logo/547423/Utrice-Leid-Album-Art.jpg",
        "width": 144
      },
      "owner": {
        "email": "jtaubenfeld@garynull.com",
        "name": "Progressive Radio Network"
      },
      "published": {
        "string": "Thu, 12 Mar 2015 21:05:57 +0000",
        "timestamp": "1426212357"
      },
      "subtitle": "Stories and news that affect us all",
      "title": "Leid Stories"
    },
    "tags": [
      "Society & Culture",
      "leid-stories"
    ],
    "title": "Obama Goes A-Gunning In Europe, Itching for A Fight"
  },
  "title": "Obama Goes A-Gunning In Europe, Itching for A Fight",
  "date": "2014-06-05 00:00:00 -0400",
  "categories": [
    "leid-stories"
  ],
  "content": "<p>A week after announcing plans for total troop withdrawal from Afghanistan by 2016, President Barack Obama seemed to be<span class=\"ellipsis\">...</span>\n&lt;!--more--&gt;\nitching for a fight in Europe.<br />\n  \nIn Poland to meet with regional leaders prior to the G7 Summit in Brussels, the president keynoted official ceremonies in Warsaw for Polish Freedom Day, marking the 25th anniversary of Poland’s emergence from communism. <br />\nIn a scathing attack on Russia—which G7 member-nations  have excluded from the summit because of its role in Ukraine—Obama told President Bronislaw Komorowski and the  people assembled that the United States is committed to defending all European states against incursions by the communist regime. <br />\nA US military buildup is already under way, Obama said.\n<br />\nLeid Stories and listeners analyze Obama’s speech, which was riddled with huge ironies and contradictions, and a reversion to the Cold War-era mindset. \n<br /></p>\n"
}
