{
  "header": {
    "category": "richard-martins-wake-up-call",
    "image": {
      "type": "",
      "url": ""
    },
    "layout": "podcast",
    "link": "http://richardmartinswakeupcall.podbean.com/e/the-rise-of-the-us-dollar-putting-it-all-together-021315-1426125691/",
    "podcast": {
      "developer-note": "",
      "length": "",
      "note": "",
      "size": 47023,
      "type": "image/jpeg",
      "url": "http://richardmartinswakeupcall.podbean.com/mf/feed/e5t3u4/image001.jpg"
    },
    "show": {
      "category": [
        "News & Politics"
      ],
      "image": {
        "height": 144,
        "url": "http://imglogo.podbean.com/image-logo/742490/TheWakeUpCallNewLogo.jpg",
        "width": 144
      },
      "owner": {
        "email": "donaldwarren@me.com",
        "name": "Richard Martin"
      },
      "published": {
        "string": "Thu, 12 Mar 2015 02:15:40 +0000",
        "timestamp": "1426144540"
      },
      "subtitle": "Richard Martin reviews the up to the minute events shaping your future in policy, economics, and world events.",
      "title": "Richard Martins   Wake Up Call"
    },
    "tags": [
      "News & Politics",
      "richard-martins-wake-up-call"
    ],
    "title": "The Rise Of the U.S. Dollar: Putting It All Together"
  },
  "title": "The Rise Of the U.S. Dollar: Putting It All Together",
  "date": "2015-02-13 00:00:00 -0500",
  "categories": [
    "richard-martins-wake-up-call"
  ],
  "content": "<p>A number of important reasons exist as to why the dollar will remain strong for the foreseeable future.\n&lt;!--more--&gt;\nThis has nothing whatever to do with the economy, a fact which most analysts have a hard time coming to terms with. <br />\nWhere to put money in the most secure investment. <br />\nThe lessons of Las Vegas when it comes to taking personal responsibility for not only your wins but also for you losses in life. <br />\nThe TTIP (the European so-called ‘free-trade’ agreement with the United States and the exact equivalent with the TTP which covers Asia) will not be ratified by the new Greek government which has veto power over its adoption. <br />\nWhatever action Greece takes in its quest to deal with its debts will doom it. <br />\nSimilarly with the United States. <br />\nThe consequences are longer-term but no less injurious. <br />\nChina’s GDP problem mirrors Greece’s precisely. <br />\nA new su […]<br /></p>\n"
}
